dataq_di_245/__init__.py
dataq_di_245/_version.py
dataq_di_245/driver.py
dataq_di_245/tests/__init__.py
dataq_di_245/tests/conftest.py
dataq_di_245/tests/test_examples.py
dataq_di_245-0.0.8.dist-info/AUTHORS.rst
dataq_di_245-0.0.8.dist-info/LICENSE
dataq_di_245-0.0.8.dist-info/METADATA
dataq_di_245-0.0.8.dist-info/WHEEL
dataq_di_245-0.0.8.dist-info/entry_points.txt
dataq_di_245-0.0.8.dist-info/top_level.txt
dataq_di_245-0.0.8.dist-info/RECORD
