Metadata-Version: 2.1
Name: dataq-di-245
Version: 0.0.8
Summary: Dataq DI-245 Data Acquisition unit
Home-page: https://github.com/vstadnytskyi/dataq-di-245
Author: Valentyn Stadnytskyi
Author-email: v.stadnytskyi@gmail.com
License: BSD (3-clause)
Platform: UNKNOWN
Classifier: Development Status :: 2 - Pre-Alpha
Classifier: Natural Language :: English
Classifier: Programming Language :: Python :: 3
Requires-Python: >=3.6
Requires-Dist: numpy
Requires-Dist: circular-buffer-numpy
Requires-Dist: pyserial
Requires-Dist: msgpack
Requires-Dist: msgpack-numpy
